archbyte/__init__.py
archbyte/telecemper.py
archbyte/tetbot.py
archbyte-0.2.2.dist-info/licenses/LICENSE
archbyte-0.2.2.dist-info/METADATA
archbyte-0.2.2.dist-info/WHEEL
archbyte-0.2.2.dist-info/top_level.txt
archbyte-0.2.2.dist-info/RECORD
