Metadata-Version: 2.4
Name: archbyte
Version: 0.2.2
Summary: A Python library for Telegram automation and group management
Home-page: https://github.com/xcophtew/archbyte
Author: Cyrus Arch
Author-email: server.arch@tuta.io
Project-URL: Bug Reports, https://github.com/xcophtew/archbyte/issues
Project-URL: Source, https://github.com/xcophtew/archbyte
Keywords: telegram automation bot group management spam-detection
Classifier: Development Status :: 3 - Alpha
Classifier: Intended Audience :: Developers
Classifier: Topic :: Communications :: Chat
Classifier: Topic :: Software Development :: Libraries :: Python Modules
Classifier: License :: OSI Approved :: MIT License
Classifier: Programming Language :: Python :: 3
Classifier: Programming Language :: Python :: 3.8
Classifier: Programming Language :: Python :: 3.9
Classifier: Programming Language :: Python :: 3.10
Classifier: Programming Language :: Python :: 3.11
Classifier: Programming Language :: Python :: 3.12
Requires-Python: >=3.8
License-File: LICENSE
Requires-Dist: telethon>=1.24.0
Dynamic: author
Dynamic: author-email
Dynamic: classifier
Dynamic: description
Dynamic: description-content-type
Dynamic: home-page
Dynamic: keywords
Dynamic: license-file
Dynamic: project-url
Dynamic: requires-dist
Dynamic: requires-python
Dynamic: summary
